myErp/__init__.py
myErp/erp.py
myErp-5.1.dist-info/LICENSE.txt
myErp-5.1.dist-info/METADATA
myErp-5.1.dist-info/WHEEL
myErp-5.1.dist-info/entry_points.txt
myErp-5.1.dist-info/top_level.txt
myErp-5.1.dist-info/zip-safe
myErp-5.1.dist-info/RECORD
